backto1/__init__.py
backto1/__main__.py
backto1/conv.py
backto1-0.0.3.dist-info/LICENSE
backto1-0.0.3.dist-info/METADATA
backto1-0.0.3.dist-info/WHEEL
backto1-0.0.3.dist-info/entry_points.txt
backto1-0.0.3.dist-info/top_level.txt
backto1-0.0.3.dist-info/RECORD
