Metadata-Version: 2.1
Name: backto1
Version: 0.0.3
Summary: A small command line tool for converting openLCA 2 JSON packages back to version 1.
Project-URL: Homepage, https://github.com/GreenDelta/backto1
Project-URL: Bug Tracker, https://github.com/GreenDelta/backto1/issues
Keywords: openLCA,life cycle assessment,LCA
Classifier: Development Status :: 2 - Pre-Alpha
Classifier: Programming Language :: Python :: 3
Classifier: License :: OSI Approved :: Mozilla Public License 2.0 (MPL 2.0)
Classifier: Operating System :: OS Independent
Classifier: Environment :: Console
Classifier: Intended Audience :: Science/Research
Classifier: Topic :: Utilities
Requires-Python: >=3.11
License-File: LICENSE
Requires-Dist: olca-schema (>=0.0.9)
